SVT_package/Ballot.py
SVT_package/Candidate.py
SVT_package/Election.py
SVT_package/__init__.py
star_voting_tool-0.5.0.dist-info/METADATA
star_voting_tool-0.5.0.dist-info/WHEEL
star_voting_tool-0.5.0.dist-info/top_level.txt
star_voting_tool-0.5.0.dist-info/RECORD
