Metadata-Version: 2.1
Name: star-voting-tool
Version: 0.5.0
Summary: This tool is created to help faciliate the adoption of STAR elections in an open and transparent manner.
Home-page: https://github.com/jaickler/SVT
Author: Jaickler
Author-email: jacobsawesomenessof@gmail.com
Project-URL: Docs, https://github.com/jaickler/SVT
Classifier: Programming Language :: Python :: 3
Classifier: License :: OSI Approved :: GNU General Public License v3 (GPLv3)
Classifier: Operating System :: OS Independent
Requires-Python: >=3.6
